[{"price":{"price":5000000.0,"discount":0.0},"address":"Kemuning Raya","size":40,"accountId":0,"facility":[],"bedType":"KING","city":"JAKARTA","name":"Room 69","booked":[],"id":0},{"price":{"price":5000000.0,"discount":0.0},"address":"Kemuning Raya","size":40,"accountId":0,"facility":["AC","WiFi"],"bedType":"KING","city":"JAKARTA","name":"Room 69","booked":[],"id":1},{"price":{"price":2.0,"discount":0.0},"address":"d","size":22,"accountId":0,"facility":["Refrigerator"],"bedType":"DOUBLE","city":"BALI","name":"aa","booked":["Dec 22, 2022, 12:00:00 AM","Jun 1, 2023, 12:00:00 AM","Jun 2, 2023, 12:00:00 AM","Jun 3, 2023, 12:00:00 AM"],"id":2},{"price":{"price":2.0,"discount":0.0},"address":"a","size":22,"accountId":0,"facility":["Refrigerator"],"bedType":"DOUBLE","city":"JAKARTA","name":"a","booked":[],"id":3},{"price":{"price":550000.0,"discount":0.0},"address":"Jl. Java Anjing","size":50,"accountId":0,"facility":["AC","Refrigerator","WiFi","Balcony","SwimmingPool","FitnessCenter"],"bedType":"DOUBLE","city":"BALI","name":"Kotlin Good","booked":["Jan 3, 2072, 12:00:00 AM","Jan 10, 2096, 12:00:00 AM","Jan 11, 2096, 12:00:00 AM","Jan 12, 2096, 12:00:00 AM","Jun 13, 2024, 12:00:00 AM","Jun 14, 2024, 12:00:00 AM","Sep 20, 2023, 12:00:00 AM","Sep 21, 2023, 12:00:00 AM","Sep 22, 2023, 12:00:00 AM","Sep 23, 2023, 12:00:00 AM","Sep 24, 2023, 12:00:00 AM","Sep 25, 2023, 12:00:00 AM","Sep 26, 2023, 12:00:00 AM"],"id":4}]